setup.py
xctrl/__init__.py
xctrl/test.py
xctrl/xctrl.py
xctrl.egg-info/PKG-INFO
xctrl.egg-info/SOURCES.txt
xctrl.egg-info/dependency_links.txt
xctrl.egg-info/top_level.txt