Metadata-Version: 2.1
Name: xctrl
Version: 0.1.0
Summary: Package for X controller
Home-page: https://github.com/prcrobo/PrecisionRobotics_xcontrol
Author: Precision Robotics
Author-email: prcrobo@gmail.com
License: MIT
Keywords: xcontrol,motor,motor control,xctrl
Platform: UNKNOWN
